vhdl/moore-machine/rising-edge-detector/rising_edge_detector.vhd
library IEEE;
use IEEE.std_logic_1164.all;

------------------------------------
-- Rising Edge Detector           --
------------------------------------
-- Detect a rising edge on X and  --
-- outputs a 1 on Y, else Y = 0   --
------------------------------------

entity rising_edge_detector is
    port (  X : in std_logic;
            Y : out std_logic;
            CLK : in std_logic);
end rising_edge_detector;

architecture arch_rising_edge_detector of rising_edge_detector is
    type state_type is (ST0, ST1, ST2);
    signal PS,NS : state_type;
begin

    -- On Clock rising edge, transition to next state
    sync_proc: process(CLK, NS)
    begin
        if (rising_edge(CLK)) then
            PS <= NS;
        end if;
    end process sync_proc;

    comb_proc: process(PS, X)
    begin
        Y <= '0'; -- pre-assign output
        case PS is
            when ST0 => -- State 0
                Y <= '0'; -- Moore Output
                -- Assign next state --
                if (X = '1') then NS <= ST1;
                else NS <= ST0;
                end if;
            when ST1 => -- State 1
                Y <= '1'; -- Moore Output
                -- Assign next state --
                if (X = '1') then NS <= ST2;
                else NS <= ST0;
                end if;
            when ST2 => -- State 0
                Y <= '0'; -- Moore Output
                -- Assign next state --
                if (X = '0') then NS <= ST0;
                else NS <= ST2;
                end if;
            when others => -- catch-all condition
                -- It should never reach this anyways
                Y <= '0';
                NS <= ST0;
        end case;
    end process comb_proc;
end arch_rising_edge_detector;

vhdl/mealy-machine/tb_rising_edge_detector.vhd
library IEEE;
use IEEE.std_logic_1164.all;

entity tb_rising_edge_detector is
end entity tb_rising_edge_detector;

architecture sim of tb_rising_edge_detector is
    constant CLK_PERIOD : time := 10 ns;

    signal clk : std_logic := '0';
    signal x   : std_logic := '0';
    signal y   : std_logic;
begin

    -- Clock generation (100 MHz)
    clk <= not clk after CLK_PERIOD / 2;

    -- Device Under Test (DUT)
    dut: entity work.rising_edge_detector
        port map (
            CLK => clk,
            X   => x,
            Y   => y
        );

    -- Stimulus process
    stim_proc: process
    begin
        wait for 15 ns;

        -- First rising edge on X
        x <= '1';
        wait for 40 ns; -- X stays High across multiple clock cycles

        -- Falling edge on X
        x <= '0';
        wait for 20 ns;

        -- Second rising edge on X
        x <= '1';
        wait for 30 ns;

        x <= '0';
        wait;
    end process;

end architecture sim;

vhdl/moore-machine/rising-edge-detector/wave.vcd
$date
  Tue Oct  6 21:07:39 2026
$end
$version
  GHDL v0
$end
$timescale
  1 fs
$end
$scope module standard $end
$upscope $end
$scope module std_logic_1164 $end
$upscope $end
$scope module tb_rising_edge_detector $end
$var reg 1 ! clk $end
$var reg 1 " x $end
$var reg 1 # y $end
$scope module dut $end
$var reg 1 $ x $end
$var reg 1 % y $end
$var reg 1 & clk $end
$comment ps is not handled $end
$comment ns is not handled $end
$upscope $end
$upscope $end
$enddefinitions $end
#0
0!
0"
0#
0$
0%
0&
#5000000
1!
1&
#10000000
0!
0&
#15000000
1!
1"
1$
1&
#20000000
0!
0&
#25000000
1!
1#
1%
1&
#30000000
0!
0&
#35000000
1!
0#
0%
1&
#40000000
0!
0&
#45000000
1!
1&
#50000000
0!
0&
#55000000
1!
0"
0$
1&
#60000000
0!
0&
#65000000
1!
1&
#70000000
0!
0&
#75000000
1!
1"
1$
1&
#80000000
0!
0&
#85000000
1!
1#
1%
1&
#90000000
0!
0&
#95000000
1!
0#
0%
1&
#100000000
0!
0&
#105000000
1!
0"
0$
1&
